<?xml version = '1.0' encoding = 'UTF-8'?>
<DataTypesDesign class="oracle.dbtools.crest.model.design.datatypes.DataTypesDesign" name="DataTypes" id="969C6668-16A6-E6EC-5992-5FAD62EFAD8F" mainViewID="B6A099D4-795B-6283-F710-D22F134C41C1">
<createdBy>ErickVladimir</createdBy>
<createdTime>2017-03-07 16:04:53 UTC</createdTime>
<ownerDesignName>bd_linkedin</ownerDesignName>
<shouldBeOpen>false</shouldBeOpen>
<collectionOfRefsPrefix>array_ref_</collectionOfRefsPrefix>
<collectionPrefix>array_</collectionPrefix>
<defaultArrayLimit>10</defaultArrayLimit>
<defaultCollectionType_Kind>ARRAY</defaultCollectionType_Kind>
<defaultCollectionType_Suffix>_Array</defaultCollectionType_Suffix>
<embeddedStructuredTypePrefix>inst_</embeddedStructuredTypePrefix>
<referencePrefix>ref_</referencePrefix>
<useRoleInAssociationEndAsName>true</useRoleInAssociationEndAsName>
</DataTypesDesign>